[
{"attribute": "Dark Hair" ,
"count": 323},
{"attribute": "Purple Hair" ,
"count": 2356},
{"attribute": "Gold Chain" ,
"count": 457},
{"attribute": "Medical Mask" ,
"count": 457},
{"attribute": "Pencil" ,
"count": 23},
{"attribute": "Purple Lipstick" ,
"count": 4578},
{"attribute": "Silver Chain" ,
"count": 67},
{"attribute": "Vampire Hair" ,
"count": 866},
{"attribute": "Blonde Bob" ,
"count": 343},
{"attribute": "pen" ,
"count": 323},
{"attribute": "ear" ,
"count": 1212},
{"attribute": "mouse" ,
"count": 122},
{"attribute": "phone" ,
"count": 3468},
{"attribute": "Candle" ,
"count": 65568},
{"attribute": "Mobile" ,
"count": 4588},
{"attribute": "Pigtails" ,
"count": 34346},
{"attribute": "Knife" ,
"count": 3467},
{"attribute": "Welding Googles" ,
"count": 235},
{"attribute": "Buck Teeth" ,
"count": 231},
{"attribute": "Orange Side" ,
"count": 124},
{"attribute": "Tiara" ,
"count": 1235},
{"attribute": "Pilot Helmet" ,
"count": 345},
{"attribute": "Choker" ,
"count": 456},
{"attribute": "Beanie" ,
"count": 567}

]
